Workbook

Sheet Summary
A1: SUNDIAL: budget to build the nine panels
A2: Draft, 25 Oct 2026. Hardware, the first event, and yearly running costs (Sole and the event).
A4: Node | B4: Cost (€) | C4: Share
A5: Panels and boards | B5: =SUMIFS(Lines!$E$2:$E$34,Lines!$A$2:$A$34,A5,Lines!$H$2:$H$34,"Yes") | C5: =IFERROR(B5/$B$11,0)
A6: Sundial hardware | B6: =SUMIFS(Lines!$E$2:$E$34,Lines!$A$2:$A$34,A6,Lines!$H$2:$H$34,"Yes") | C6: =IFERROR(B6/$B$11,0)
A7: Mounting and plates | B7: =SUMIFS(Lines!$E$2:$E$34,Lines!$A$2:$A$34,A7,Lines!$H$2:$H$34,"Yes") | C7: =IFERROR(B7/$B$11,0)
A8: The event (2027) | B8: =SUMIFS(Lines!$E$2:$E$34,Lines!$A$2:$A$34,A8,Lines!$H$2:$H$34,"Yes") | C8: =IFERROR(B8/$B$11,0)
A9: Website, permissions, insurance | B9: =SUMIFS(Lines!$E$2:$E$34,Lines!$A$2:$A$34,A9,Lines!$H$2:$H$34,"Yes") | C9: =IFERROR(B9/$B$11,0)
A10: Shared and spares | B10: =SUMIFS(Lines!$E$2:$E$34,Lines!$A$2:$A$34,A10,Lines!$H$2:$H$34,"Yes") | C10: =IFERROR(B10/$B$11,0)
A11: Build subtotal | B11: =SUM(B5:B10)
A12: Contingency | B12: =B11*B17
A13: Build total | B13: =B11+B12
A14: Each following year: insurance, domain, upkeep, the year's print | B14: =SUMIFS(Lines!$E$2:$E$34,Lines!$A$2:$A$34,"Running, each year",Lines!$H$2:$H$34,"Yes")
A15: Total to build and run the first year | B15: =B13
A17: Contingency rate | B17: 0.15
A19: Option, not in the total:
A20: Post panel (in place of one wall) | B20: =SUMIFS(Lines!$E$2:$E$34,Lines!$A$2:$A$34,"Post option")
A22: How to use it
A23: Edit only the blue cells: quantities, unit prices and Include (Yes/No) on the Lines sheet, and the contingency rate above (yellow).
A24: Basis on each line: Quote (from the supplier), Listed price (seen online, Oct 2026), Estimate (to be confirmed).
A25: Prices include VAT. The first year's insurance, domain and print are in the build cost; the yearly figure starts from the second year.
A26: To include a post panel, set its lines' Include to Yes on the Lines sheet.
A27: Not included: PVA's labour and travel; the print's sale income.

Sheet Lines
A1: Node | B1: Item | C1: Qty | D1: Unit (€) | E1: Total (€) | F1: Basis | G1: Source / note | H1: Include
A2: Panels and boards | B2: Retired PV panel, Trina TSM-185DC01 class (9 + 1 spare) | C2: 10 | D2: 30 | E2: =C2*D2 | F2: Estimate | G2: Second-hand / end-of-life; may be donated. Source still to confirm | H2: Yes
A3: Panels and boards | B3: Board designer: schematic review, layout, files (CARRIER.md brief) | C3: 1 | D3: 1000 | E3: =C3*D3 | F3: Estimate | G3: One-off; get quotes (Italian/European design house) | H3: Yes
A4: Panels and boards | B4: Carrier v1, small run of 5, assembled (bench test of the sun sensor) | C4: 5 | D4: 100 | E4: =C4*D4 | F4: Estimate | G4: Small-run setup costs make v1 dear per board | H4: Yes
A5: Panels and boards | B5: Carrier v2, run of 10, assembled (9 panels + 1 spare) | C5: 10 | D5: 60 | E5: =C5*D5 | F5: Estimate | G5: CARRIER.md: order 5 of v1, fix, then 10 of v2 | H5: Yes
A6: Panels and boards | B6: ELEGOO ESP32 30-pin dev boards (v1 bench + v2) | C6: 15 | D6: 9 | E6: =C6*D6 | F6: Estimate | H6: Yes
A7: Panels and boards | B7: Buck converter modules (8–60 V in, 5 V out) | C7: 15 | D7: 5 | E7: =C7*D7 | F7: Estimate | H7: Yes
A8: Panels and boards | B8: Supercapacitor pairs (2 x 10 F), DS18B20 probe, CR2032 | C8: 10 | D8: 12 | E8: =C8*D8 | F8: Estimate | H8: Yes
A9: Panels and boards | B9: IP65 box, glands, breather vent, tamper screws | C9: 10 | D9: 32 | E9: =C9*D9 | F9: Estimate | G9: CARRIER.md: about 150 x 110 x 70 mm | H9: Yes
A10: Panels and boards | B10: Cable, fuses, terminals | C10: 10 | D10: 15 | E10: =C10*D10 | F10: Estimate | H10: Yes
A11: Sundial hardware | B11: Gnomon: 15 mm aluminium tube, 45 cm, TIG-welded to its mount | C11: 9 | D11: 40 | E11: =C11*D11 | F11: Estimate | G11: Local fabrication; GNOMON.md | H11: Yes
A12: Sundial hardware | B12: Hour lines and date marks: UV-stable vinyl pinstripe tape, per panel | C12: 9 | D12: 10 | E12: =C12*D12 | F12: Estimate | G12: No numbers, no brackets; GNOMON.md | H12: Yes
A13: Sundial hardware | B13: Stand-offs (aluminium angle) and M6 stainless fixings | C13: 9 | D13: 30 | E13: =C13*D13 | F13: Estimate | H13: Yes
A14: Sundial hardware | B14: Hour-line tape test (pilot panel) | C14: 1 | D14: 20 | E14: =C14*D14 | F14: Estimate | G14: README to-do | H14: Yes
A15: Mounting and plates | B15: Wall fixings (anchors, brackets) | C15: 9 | D15: 25 | E15: =C15*D15 | F15: Estimate | H15: Yes
A16: Mounting and plates | B16: Wall plate: number and QR code | C16: 9 | D16: 20 | E16: =C16*D16 | F16: Estimate | H16: Yes
A17: The event (2027) | B17: Girasole: dwarf sunflowers, pots, soil | C17: 1 | D17: 40 | E17: =C17*D17 | F17: Estimate | H17: Yes
A18: The event (2027) | B18: Girasole: chalkboard, stand, ochre and blue chalk | C18: 1 | D18: 90 | E18: =C18*D18 | F18: Estimate | H18: Yes
A19: The event (2027) | B19: Flyers | C19: 1 | D19: 100 | E19: =C19*D19 | F19: Estimate | H19: Yes
A20: The event (2027) | B20: Screen print set-up: four screens and films | C20: 1 | D20: 400 | E20: =C20*D20 | F20: Estimate | G20: Awaiting the print shop's answer (texts/print-enquiry.md) | H20: Yes
A21: The event (2027) | B21: Screen print run | C21: 50 | D21: 10 | E21: =C21*D21 | F21: Estimate | G21: Edition size and price per print still open; sales may cover it | H21: Yes
A22: Website, permissions, insurance | B22: Domain photovoltaic.art, first year | C22: 1 | D22: 30 | E22: =C22*D22 | F22: Estimate | G22: Check the renewal price (PVA TASKS.md) | H22: Yes
A23: Website, permissions, insurance | B23: Public liability insurance, first year | C23: 1 | D23: 400 | E23: =C23*D23 | F23: Estimate | G23: Get a quote | H23: Yes
A24: Website, permissions, insurance | B24: Permission costs (applications, stamps) | C24: 1 | D24: 100 | E24: =C24*D24 | F24: Estimate | G24: Depends on the route: patto di collaborazione or authorisation | H24: Yes
A25: Shared and spares | B25: Spares: supercaps, coin cells, probe, fixings | C25: 1 | D25: 60 | E25: =C25*D25 | F25: Estimate | G25: SUNDIAL.md 5 | H25: Yes
A26: Shared and spares | B26: Bench supply and test leads | C26: 1 | D26: 60 | E26: =C26*D26 | F26: Estimate | G26: If not already owned | H26: Yes
A27: Shared and spares | B27: Shipping | C27: 1 | D27: 100 | E27: =C27*D27 | F27: Estimate | H27: Yes
A28: Post option | B28: Steel post and base | C28: 1 | D28: 450 | E28: =C28*D28 | F28: Estimate | G28: Only where no wall works (POST.md) | H28: No
A29: Post option | B29: Structural engineer's sign-off | C29: 1 | D29: 400 | E29: =C29*D29 | F29: Estimate | H29: No
A30: Post option | B30: USB-C PD charger module, sockets, shelf, plate | C30: 1 | D30: 110 | E30: =C30*D30 | F30: Estimate | H30: No
A31: Running, each year | B31: Insurance renewal | C31: 1 | D31: 400 | E31: =C31*D31 | F31: Estimate | H31: Yes
A32: Running, each year | B32: Domain renewal | C32: 1 | D32: 30 | E32: =C32*D32 | F32: Estimate | H32: Yes
A33: Running, each year | B33: Upkeep: coin cells, supercaps over time, cleaning | C33: 1 | D33: 60 | E33: =C33*D33 | F33: Estimate | H33: Yes
A34: Running, each year | B34: Screen print set-up for the year's print | C34: 1 | D34: 400 | E34: =C34*D34 | F34: Estimate | G34: Each event makes a new print | H34: Yes
